java-stubs/__init__.pyi
java-stubs/lang/__init__.pyi
java-stubs/lang/annotation/__init__.pyi
java-stubs/lang/constant/__init__.pyi
java-stubs/lang/instrument/__init__.pyi
java-stubs/lang/invoke/__init__.pyi
java-stubs/lang/management/__init__.pyi
java-stubs/lang/module/__init__.pyi
java-stubs/lang/ref/__init__.pyi
java-stubs/lang/reflect/__init__.pyi
java-stubs/lang/runtime/__init__.pyi
java-stubs/time/__init__.pyi
java-stubs/time/chrono/__init__.pyi
java-stubs/time/format/__init__.pyi
java-stubs/time/temporal/__init__.pyi
java-stubs/time/zone/__init__.pyi
java-stubs/util/__init__.pyi
java-stubs/util/concurrent/__init__.pyi
java-stubs/util/concurrent/atomic/__init__.pyi
java-stubs/util/concurrent/locks/__init__.pyi
java-stubs/util/function/__init__.pyi
java-stubs/util/jar/__init__.pyi
java-stubs/util/logging/__init__.pyi
java-stubs/util/prefs/__init__.pyi
java-stubs/util/random/__init__.pyi
java-stubs/util/regex/__init__.pyi
java-stubs/util/spi/__init__.pyi
java-stubs/util/stream/__init__.pyi
java-stubs/util/zip/__init__.pyi
jpyinterpreter/__init__.py
jpyinterpreter/jvm_setup.py
jpyinterpreter/python_to_java_bytecode_translator.py
jpype-stubs/__init__.pyi
optapy/__init__.py
optapy/annotations.py
optapy/classpath.txt
optapy/constraint_stream.py
optapy/jpype_type_conversions.py
optapy/optaplanner_api_wrappers.py
optapy/optaplanner_java_interop.py
optapy/optaplanner_python_logger.py
optapy/config/__init__.py
optapy/constraint/__init__.py
optapy/jars/HdrHistogram-2.1.12.jar
optapy/jars/LatencyUtils-2.0.3.jar
optapy/jars/__init__.py
optapy/jars/angus-activation-2.0.0.jar
optapy/jars/antlr-runtime-3.5.2.jar
optapy/jars/apiguardian-api-1.1.2.jar
optapy/jars/asm-9.5.jar
optapy/jars/asm-analysis-9.5.jar
optapy/jars/asm-tree-9.5.jar
optapy/jars/asm-util-9.5.jar
optapy/jars/assertj-core-3.24.2.jar
optapy/jars/byte-buddy-1.12.18.jar
optapy/jars/byte-buddy-agent-1.14.1.jar
optapy/jars/commons-codec-1.15.jar
optapy/jars/commons-collections4-4.4.jar
optapy-9.37.0b0.dist-info/LICENSE
optapy-9.37.0b0.dist-info/METADATA
optapy-9.37.0b0.dist-info/WHEEL
optapy-9.37.0b0.dist-info/top_level.txt
optapy-9.37.0b0.dist-info/RECORD
