Metadata-Version: 2.1
Name: optapy
Version: 9.37.0b0
Summary: An AI constraint solver that optimizes planning and scheduling problems
Home-page: https://github.com/optapy/optapy
License: Apache License Version 2.0
Project-URL: OptaPy Documentation, https://optapy.org
Project-URL: OptaPlanner Homepage, https://www.optaplanner.org/
Platform: UNKNOWN
Classifier: Development Status :: 4 - Beta
Classifier: Programming Language :: Python :: 3
Classifier: Topic :: Scientific/Engineering :: Artificial Intelligence
Classifier: Topic :: Software Development :: Libraries :: Java Libraries
Classifier: License :: OSI Approved :: Apache Software License
Classifier: Operating System :: OS Independent
Requires-Python: >=3.9
License-File: LICENSE
Requires-Dist: JPype1 (>=1.4.1)
